fillplace/__init__.py
fillplace/placeholders.py
fillplace-1.0.0.dist-info/METADATA
fillplace-1.0.0.dist-info/WHEEL
fillplace-1.0.0.dist-info/top_level.txt
fillplace-1.0.0.dist-info/RECORD
