Metadata-Version: 2.1
Name: fillplace
Version: 1.0.0
Summary: A package for generating meaningful placeholder content.
Home-page: https://github.com/Kunal-Khairnar-05/fillplace
Author: Kunal Khairnar
Author-email: kunalkhairnar2005@gmail.com
License: UNKNOWN
Platform: UNKNOWN
Classifier: Programming Language :: Python :: 3
Classifier: License :: OSI Approved :: MIT License
Classifier: Operating System :: OS Independent
Requires-Python: >=3.6
Requires-Dist: requests
